omuplugin_archive/__init__.py
omuplugin_archive/archive.py
omuplugin_archive/const.py
omuplugin_archive/plugin.py
omuplugin_archive/types.py
omuplugin_archive/version.py
omuplugin_archive-0.9.24.dist-info/METADATA
omuplugin_archive-0.9.24.dist-info/WHEEL
omuplugin_archive-0.9.24.dist-info/entry_points.txt
omuplugin_archive-0.9.24.dist-info/RECORD
